kubectl_show/__init__.py
kubectl_show/main.py
kubectl_show/cli/__init__.py
kubectl_show/cli/base.py
kubectl_show/cli/generate.py
kubectl_show/cli/query.py
kubectl_show/default_templates/__init__.py
kubectl_show/default_templates/nginx/__init__.py
kubectl_show/j2_templates/__init__.py
kubectl_show/j2_templates/clusterrolebinding.j2.yaml
kubectl_show/j2_templates/daemonset.j2.yaml
kubectl_show/j2_templates/deployment.j2.yaml
kubectl_show/j2_templates/service.j2.yaml
kubectl_show-22.1.0.23.dist-info/LICENSE
kubectl_show-22.1.0.23.dist-info/METADATA
kubectl_show-22.1.0.23.dist-info/WHEEL
kubectl_show-22.1.0.23.dist-info/entry_points.txt
kubectl_show-22.1.0.23.dist-info/top_level.txt
kubectl_show-22.1.0.23.dist-info/RECORD
