Metadata-Version: 2.1
Name: kubectl-show
Version: 22.1.0.23
Summary: kubectl python plugin
Home-page: https://github.com/newpi6/kubectl-show.git
Author: harvey
Author-email: harveyzhwei@gmail.com
License: MIT
Project-URL: Document, https://github.com/newpi6/kubectl-show.git
Project-URL: Source Code, https://github.com/newpi6/kubectl-show.git
Project-URL: Issue Tracker, https://github.com/newpi6/kubectl-show/issues
Keywords: kubectl,Kubernetes
Platform: UNKNOWN
Classifier: Development Status :: 5 - Production/Stable
Classifier: Topic :: Utilities
Classifier: Intended Audience :: Developers
Classifier: Intended Audience :: Information Technology
Classifier: License :: OSI Approved :: MIT License
Classifier: Operating System :: OS Independent
Classifier: Programming Language :: Python
Classifier: Programming Language :: Python :: 3
Classifier: Programming Language :: Python :: 3.6
Classifier: Programming Language :: Python :: 3.7
Classifier: Programming Language :: Python :: 3.8
Classifier: Programming Language :: Python :: 3.9
Classifier: Programming Language :: Python :: 3.10
Requires-Python: >=3.6
License-File: LICENSE
Requires-Dist: kubernetes (==22.6.0)
Requires-Dist: tabulate (>=0.8.9)
Requires-Dist: fire (>=0.4.0)
Requires-Dist: Jinja2 (>=3.1.1)
